graymatter_swissknife/__about__.py
graymatter_swissknife/__init__.py
graymatter_swissknife/__main__.py
graymatter_swissknife/compute_powder_average.py
graymatter_swissknife/estimate_model.py
graymatter_swissknife/estimate_model_noiseless.py
graymatter_swissknife/estimate_model_preinitialized.py
graymatter_swissknife/deprecated/estimate_model_folded_normal.py
graymatter_swissknife/models/__init__.py
graymatter_swissknife/models/find_model.py
graymatter_swissknife/models/microstructure_models.py
graymatter_swissknife/models/GEM/__init__.py
graymatter_swissknife/models/GEM/gem.py
graymatter_swissknife/models/GEM/gem_rm.py
graymatter_swissknife/models/GEM/functions/__init__.py
graymatter_swissknife/models/GEM/functions/scipy_gem.py
graymatter_swissknife/models/NEXI/__init__.py
graymatter_swissknife/models/NEXI/nexi.py
graymatter_swissknife/models/NEXI/nexi_dot.py
graymatter_swissknife/models/NEXI/nexi_dot_rm.py
graymatter_swissknife/models/NEXI/nexi_foldednormal.py
graymatter_swissknife/models/NEXI/nexi_rm.py
graymatter_swissknife/models/NEXI/smex.py
graymatter_swissknife/models/NEXI/smex_rm.py
graymatter_swissknife/models/NEXI/functions/scipy_nexi.py
graymatter_swissknife/models/NEXI/functions/scipy_nexi_dot.py
graymatter_swissknife/models/NEXI/functions/scipy_smex.py
graymatter_swissknife/models/SANDI/__init__.py
graymatter_swissknife/models/SANDI/sandi.py
graymatter_swissknife/models/SANDI/sandi_rm.py
graymatter_swissknife/models/SANDI/functions/__init__.py
graymatter_swissknife/models/SANDI/functions/scipy_sandi.py
graymatter_swissknife/models/SANDIX/__init__.py
graymatter_swissknife/models/SANDIX/sandix.py
graymatter_swissknife/models/SANDIX/sandix_rm.py
graymatter_swissknife/models/SANDIX/functions/__init__.py
graymatter_swissknife/models/SANDIX/functions/scipy_sandix.py
graymatter_swissknife/models/noise/__init__.py
graymatter_swissknife/models/noise/folded_normal_mean.py
graymatter_swissknife/models/noise/rice_mean.py
graymatter_swissknife-1.4.3.dist-info/METADATA
graymatter_swissknife-1.4.3.dist-info/WHEEL
graymatter_swissknife-1.4.3.dist-info/licenses/LICENSE
graymatter_swissknife-1.4.3.dist-info/RECORD
