Metadata-Version: 2.4
Name: graymatter_swissknife
Version: 1.4.3
Summary: Gray Matter Swiss Knife : Generalized Exchange Model estimators for diffusion MRI
Project-URL: Documentation, https://github.com/QuentinUhl/graymatter_swissknife#readme
Project-URL: Issues, https://github.com/QuentinUhl/graymatter_swissknife/issues
Project-URL: Source, https://github.com/QuentinUhl/graymatter_swissknife
Author-email: Quentin Uhl <quentin.uhl@gmail.com>, "Ileana O. Jelescu" <ileana.jelescu@chuv.ch>
License-Expression: Apache-2.0
License-File: LICENSE
Keywords: diffusion,dmri,grey matter,microstructure,model,mri
Classifier: Development Status :: 5 - Production/Stable
Classifier: Programming Language :: Python
Classifier: Programming Language :: Python :: 3.7
Classifier: Programming Language :: Python :: 3.8
Classifier: Programming Language :: Python :: 3.9
Classifier: Programming Language :: Python :: 3.10
Classifier: Programming Language :: Python :: 3.11
Classifier: Programming Language :: Python :: Implementation :: CPython
Classifier: Programming Language :: Python :: Implementation :: PyPy
Requires-Python: >=3.7
